finit_classifier/__init__.py
finit_classifier-0.0.1.dist-info/METADATA
finit_classifier-0.0.1.dist-info/WHEEL
finit_classifier-0.0.1.dist-info/RECORD
